{
  "package": {
    "downloadUrlList_armeabi-v7a": [
      "https://github.com/e1ch/SmartTube/releases/download/latest/SmartTube_beta_armeabi-v7a.apk"
    ],
    "downloadUrlList_arm64-v8a": [
      "https://github.com/e1ch/SmartTube/releases/download/latest/SmartTube_beta_arm64-v8a.apk"
    ],
    "downloadUrlList_x86": [
      "https://github.com/e1ch/SmartTube/releases/download/latest/SmartTube_beta_x86.apk"
    ],
    "downloadUrlList": [
      "https://github.com/e1ch/SmartTube/releases/download/latest/SmartTube_beta_universal.apk"
    ]
  },
  "31.47": {
    "versionCode": 2337,
    "changelog": [
      "Search filter: THIS_MONTH — only shows videos from last 30 days",
      "No more old/stale content in search fallback results"
    ],
    "changelog_zh": [
      "搜尋過濾：僅顯示過去一個月內的影片",
      "搜尋結果不再出現舊影片"
    ]
  },
  "31.46": {
    "versionCode": 2336,
    "changelog": [
      "Trending tab: kworb only (removed all search-based fake trending)",
      "No more '爆紅', '熱門趨勢', 'Viral', 'Hot Now' search shelves"
    ],
    "changelog_zh": [
      "熱門 Tab：僅保留 kworb 真實資料（移除所有搜尋偽熱門）",
      "不再出現「爆紅」「熱門趨勢」等搜尋結果分類"
    ]
  },
  "31.45": {
    "versionCode": 2335,
    "changelog": [
      "Removed 'Viral/爆紅' and 'Trending/熱門趨勢' low-quality search shelves",
      "Trending queries replaced: Hot Now / New Releases / Worth Watching",
      "Prefetch uses home query pools instead of trending queries",
      "All 45 languages updated"
    ],
    "changelog_zh": [
      "移除「爆紅」「熱門趨勢」低品質搜尋分類",
      "Trending 查詢替換：現在熱門 / 新上映 / 值得一看",
      "首頁預取改用 home query pool",
      "全部 45 種語言更新"
    ]
  },
  "31.44": {
    "versionCode": 2334,
    "changelog": [
      "Ranking engine: topic/channel diversity scoring (break filter bubble)",
      "Exploration pool: movies, travel, documentaries (45 languages)",
      "Duration badge on all video sources (kworb, Charts, search)",
      "Trending tab: kworb-first mixed content (not music-only)",
      "Charts music content exclusive to Music tab"
    ],
    "changelog_zh": [
      "排名引擎：類型/頻道多樣性評分（打破訊息繭房）",
      "探索池：電影、旅遊、紀錄片（45 種語言）",
      "影片長度 badge 顯示在所有來源",
      "熱門 Tab：kworb 為主（綜合內容，非僅音樂）",
      "Charts 音樂排行專屬 Music Tab"
    ]
  },
  "31.43": {
    "versionCode": 2333,
    "changelog": [
      "YouTube Charts: official trending/top/songs charts per country",
      "Home: progressive loading with streaming results",
      "Trending tab: Charts + kworb + search for full variety",
      "Duration badge on chart video thumbnails",
      "kworb trending with /player metadata (100% match rate)",
      "Search: WEB client, auth skip for signed-in users",
      "QR code sign-in: vertical layout, soft background",
      "Locale: language/country independent setting",
      "48 languages: localized search queries",
      "Performance: SplashActivity prewarm, parallel search with jitter",
      "Channel diversity: max 2 per shelf",
      "Refresh throttle: soft/medium/hard",
      "OkHttp log: BODY to BASIC (fixes logcat overflow)",
      "Update system: points to e1ch/SmartTube releases"
    ],
    "changelog_zh": [
      "YouTube 官方排行榜：依國家顯示熱門/排行/歌曲",
      "首頁：分段載入（Phase 1 即時顯示，Phase 2 串流追加）",
      "熱門 Tab：Charts + kworb + 搜尋，完整多元內容",
      "排行榜影片縮圖顯示時間長度",
      "kworb 即時熱門：/player 取得完整資訊（100% 匹配）",
      "搜尋：WEB client，登入後也正常運作",
      "QR code 登入：垂直佈局，柔和背景",
      "語言/國家：獨立設定不互相干擾",
      "48 種語言：本地化搜尋關鍵字",
      "效能：SplashActivity 預熱、並行搜尋+抖動",
      "內容多樣性：同頻道≤2",
      "Refresh 節流：soft/medium/hard",
      "OkHttp 日誌：BODY 改 BASIC（修正 logcat 溢出）",
      "更新系統：指向 e1ch/SmartTube releases"
    ]
  },
  "31.42": {
    "versionCode": 2332,
    "changelog": [
      "Initial fork from yuliskov/SmartTube"
    ]
  }
}
